LICENSE
README.md
setup.py
byteplus_sdk/ApiInfo.py
byteplus_sdk/Credentials.py
byteplus_sdk/Policy.py
byteplus_sdk/ServiceInfo.py
byteplus_sdk/ServiceInfoHttps.py
byteplus_sdk/__init__.py
byteplus_sdk.egg-info/PKG-INFO
byteplus_sdk.egg-info/SOURCES.txt
byteplus_sdk.egg-info/dependency_links.txt
byteplus_sdk.egg-info/requires.txt
byteplus_sdk.egg-info/top_level.txt
byteplus_sdk/auth/MetaData.py
byteplus_sdk/auth/SignerV4.py
byteplus_sdk/auth/__init__.py
byteplus_sdk/base/Request.py
byteplus_sdk/base/Service.py
byteplus_sdk/base/__init__.py
byteplus_sdk/base/models/__init__.py
byteplus_sdk/base/models/base/__init__.py
byteplus_sdk/base/models/base/base_pb2.py
byteplus_sdk/cdn/__init__.py
byteplus_sdk/cdn/service.py
byteplus_sdk/const/Const.py
byteplus_sdk/const/__init__.py
byteplus_sdk/example/__init__.py
byteplus_sdk/example/cdn/__init__.py
byteplus_sdk/example/cdn/add_cdn_certificate.py
byteplus_sdk/example/cdn/add_cdn_domain.py
byteplus_sdk/example/cdn/add_template_domain.py
byteplus_sdk/example/cdn/create_cipher_template.py
byteplus_sdk/example/cdn/create_rule_engine_template.py
byteplus_sdk/example/cdn/create_service_template.py
byteplus_sdk/example/cdn/delete_cdn_domain.py
byteplus_sdk/example/cdn/delete_template.py
byteplus_sdk/example/cdn/describe_accounting_data.py
byteplus_sdk/example/cdn/describe_cdn_access_log.py
byteplus_sdk/example/cdn/describe_cdn_config.py
byteplus_sdk/example/cdn/describe_cdn_data.py
byteplus_sdk/example/cdn/describe_cdn_data_detail.py
byteplus_sdk/example/cdn/describe_cdn_detail.py
byteplus_sdk/example/cdn/describe_cdn_origin_data.py
byteplus_sdk/example/cdn/describe_cdn_region_and_isp.py
byteplus_sdk/example/cdn/describe_cdn_service.py
byteplus_sdk/example/cdn/describe_cdn_upper_ip.py
byteplus_sdk/example/cdn/describe_cipher_template.py
byteplus_sdk/example/cdn/describe_content_block_tasks.py
byteplus_sdk/example/cdn/describe_content_quota.py
byteplus_sdk/example/cdn/describe_content_tasks.py
byteplus_sdk/example/cdn/describe_edge_nrt_data_summary.py
byteplus_sdk/example/cdn/describe_edge_statistical_data.py
byteplus_sdk/example/cdn/describe_edge_top_nrt_data.py
