Metadata-Version: 2.1
Name: byteplus-sdk
Version: 1.0.53
Summary: The BytePlus SDK for Python
Home-page: https://github.com/byteplus-sdk/byteplus-sdk-python
Author: BytePlus SDK
License: MIT Licence
Keywords: pip,byteplus,byteplus-sdk-python
Platform: any
License-File: LICENSE
